{
  "id": "scanner-scan-modes",
  "name": "scanner-scan-modes",
  "title": "扫描器 Web UI 增加 scan/dry-run/dump/dump-force 四种扫描模式选择",
  "description": "",
  "status": "completed",
  "dev_type": null,
  "scope": null,
  "package": null,
  "priority": "P2",
  "creator": "klz",
  "assignee": "klz",
  "createdAt": "2026-05-21",
  "completedAt": "2026-05-21",
  "branch": null,
  "base_branch": "master",
  "worktree_path": null,
  "commit": null,
  "pr_url": null,
  "subtasks": [],
  "children": [],
  "parent": null,
  "relatedFiles": [],
  "notes": "",
  "meta": {}
}